setup.py
hipmob/__init__.py
hipmob/version.py
hipmob.egg-info/PKG-INFO
hipmob.egg-info/SOURCES.txt
hipmob.egg-info/dependency_links.txt
hipmob.egg-info/top_level.txt