Metadata-Version: 1.0
Name: hipmob
Version: 0.1.0
Summary: Hipmob python bindings
Home-page: https://www.hipmob.com/
Author: Orthogonal Labs, Inc.
Author-email: team@hipmob.com
License: UNKNOWN
Platform: UNKNOWN
